<?xml version="1.0" encoding="UTF-8"?>

<samplemap CrossfadeGamma="1.0" ID="Ext_Bell4" RRGroupAmount="1.0" MicPositions=";"
           SaveMode="2">
  <sample Root="41" LoKey="0" HiKey="40" LoVel="0" HiVel="127" RRGroup="1"
          FileName="{PROJECT_FOLDER}101/FilterBell/FilterBell-37-127-K898.wav"
          Duplicate="1" LoopEnabled="1" LoopStart="191963" LoopEnd="434390"
          SampleEnd="434399" SampleRate="44100.0" MonolithOffset="0" MonolithLength="438272"/>
  <sample Root="45" LoKey="41" HiKey="44" LoVel="0" HiVel="127" RRGroup="1"
          FileName="{PROJECT_FOLDER}101/FilterBell/FilterBell-41-127-IB4I.wav"
          Duplicate="1" LoopEnabled="1" LoopStart="374797" LoopEnd="415493"
          SampleEnd="415502" SampleRate="44100.0" MonolithOffset="438272"
          MonolithLength="417792"/>
  <sample Root="49" LoKey="45" HiKey="48" LoVel="0" HiVel="127" RRGroup="1"
          FileName="{PROJECT_FOLDER}101/FilterBell/FilterBell-45-127-HGOZ.wav"
          Duplicate="1" LoopEnabled="1" LoopStart="350899" LoopEnd="418819"
          SampleEnd="418828" SampleRate="44100.0" MonolithOffset="856064"
          MonolithLength="421888"/>
  <sample Root="53" LoKey="49" HiKey="52" LoVel="0" HiVel="127" RRGroup="1"
          FileName="{PROJECT_FOLDER}101/FilterBell/FilterBell-49-127-PQTU.wav"
          Duplicate="1" LoopEnabled="1" LoopStart="371889" LoopEnd="398906"
          SampleEnd="398915" SampleRate="44100.0" MonolithOffset="1277952"
          MonolithLength="401408"/>
  <sample Root="57" LoKey="53" HiKey="56" LoVel="0" HiVel="127" RRGroup="1"
          FileName="{PROJECT_FOLDER}101/FilterBell/FilterBell-53-127-E1QE.wav"
          Duplicate="1" LoopEnabled="1" LoopStart="270719" LoopEnd="366028"
          SampleEnd="366037" SampleRate="44100.0" MonolithOffset="1679360"
          MonolithLength="368640"/>
  <sample Root="61" LoKey="57" HiKey="60" LoVel="0" HiVel="127" RRGroup="1"
          FileName="{PROJECT_FOLDER}101/FilterBell/FilterBell-57-127-17PR.wav"
          Duplicate="1" LoopEnabled="1" LoopStart="337036" LoopEnd="419477"
          SampleEnd="419486" SampleRate="44100.0" MonolithOffset="2048000"
          MonolithLength="421888"/>
  <sample Root="65" LoKey="61" HiKey="64" LoVel="0" HiVel="127" RRGroup="1"
          FileName="{PROJECT_FOLDER}101/FilterBell/FilterBell-61-127-HG7J.wav"
          Duplicate="1" LoopEnabled="1" LoopStart="258904" LoopEnd="451177"
          SampleEnd="451186" SampleRate="44100.0" MonolithOffset="2469888"
          MonolithLength="454656"/>
  <sample Root="69" LoKey="65" HiKey="68" LoVel="0" HiVel="127" RRGroup="1"
          FileName="{PROJECT_FOLDER}101/FilterBell/FilterBell-65-127-ZW84.wav"
          Duplicate="1" LoopEnabled="1" LoopStart="318396" LoopEnd="411981"
          SampleEnd="411990" SampleRate="44100.0" MonolithOffset="2924544"
          MonolithLength="413696"/>
  <sample Root="73" LoKey="69" HiKey="127" LoVel="0" HiVel="127" RRGroup="1"
          FileName="{PROJECT_FOLDER}101/FilterBell/FilterBell-69-127-YJVG.wav"
          Duplicate="1" LoopEnabled="1" LoopStart="298443" LoopEnd="385591"
          SampleEnd="385600" SampleRate="44100.0" MonolithOffset="3338240"
          MonolithLength="389120"/>
</samplemap>
