<?xml version="1.0" encoding="UTF-8"?>

<samplemap CrossfadeGamma="1.0" ID="PuddinCrd1" RRGroupAmount="1.0" MicPositions=";"
           SaveMode="2">
  <sample Root="58" LoKey="58" HiKey="58" LoVel="0" HiVel="127" RRGroup="1"
          FileName="/Users/rick/Downloads/mod/PuddinChord/PuddinChord-A#2-15-9SKL.aif"
          Duplicate="0" LoopEnabled="1" LoopStart="268574" LoopEnd="335129"
          SampleEnd="454976" SampleRate="44100.0" MonolithOffset="0" MonolithLength="458752"/>
  <sample Root="70" LoKey="70" HiKey="70" LoVel="0" HiVel="127" RRGroup="1"
          FileName="/Users/rick/Downloads/mod/PuddinChord/PuddinChord-A#3-15-WMMQ.aif"
          Duplicate="0" LoopEnabled="1" LoopStart="183486" LoopEnd="365470"
          SampleEnd="453952" SampleRate="44100.0" MonolithOffset="458752"
          MonolithLength="454656"/>
  <sample Root="57" LoKey="57" HiKey="57" LoVel="0" HiVel="127" RRGroup="1"
          FileName="/Users/rick/Downloads/mod/PuddinChord/PuddinChord-A2-15-CQUM.aif"
          Duplicate="0" LoopEnabled="1" LoopStart="291729" LoopEnd="329592"
          SampleEnd="454304" SampleRate="44100.0" MonolithOffset="913408"
          MonolithLength="454656"/>
  <sample Root="69" LoKey="69" HiKey="69" LoVel="0" HiVel="127" RRGroup="1"
          FileName="/Users/rick/Downloads/mod/PuddinChord/PuddinChord-A3-15-QQ9N.aif"
          Duplicate="0" LoopEnabled="1" LoopStart="226839" LoopEnd="275306"
          SampleEnd="453504" SampleRate="44100.0" MonolithOffset="1368064"
          MonolithLength="454656"/>
  <sample Root="59" LoKey="59" HiKey="59" LoVel="0" HiVel="127" RRGroup="1"
          FileName="/Users/rick/Downloads/mod/PuddinChord/PuddinChord-B2-15-YXYD.aif"
          Duplicate="0" LoopEnabled="1" LoopStart="181999" LoopEnd="364349"
          SampleEnd="453568" SampleRate="44100.0" MonolithOffset="1822720"
          MonolithLength="454656"/>
  <sample Root="71" LoKey="71" HiKey="71" LoVel="0" HiVel="127" RRGroup="1"
          FileName="/Users/rick/Downloads/mod/PuddinChord/PuddinChord-B3-15-SDCF.aif"
          Duplicate="0" LoopEnabled="1" LoopStart="176245" LoopEnd="300746"
          SampleEnd="455424" SampleRate="44100.0" MonolithOffset="2277376"
          MonolithLength="458752"/>
  <sample Root="49" LoKey="49" HiKey="49" LoVel="0" HiVel="127" RRGroup="1"
          FileName="/Users/rick/Downloads/mod/PuddinChord/PuddinChord-C#2-15-MKCS.aif"
          Duplicate="0" LoopEnabled="1" LoopStart="229418" LoopEnd="335026"
          SampleEnd="454592" SampleRate="44100.0" MonolithOffset="2736128"
          MonolithLength="454656"/>
  <sample Root="61" LoKey="61" HiKey="61" LoVel="0" HiVel="127" RRGroup="1"
          FileName="/Users/rick/Downloads/mod/PuddinChord/PuddinChord-C#3-15-U5P0.aif"
          Duplicate="0" LoopEnabled="1" LoopStart="238392" LoopEnd="354782"
          SampleEnd="454240" SampleRate="44100.0" MonolithOffset="3190784"
          MonolithLength="454656"/>
  <sample Root="48" LoKey="5" HiKey="48" LoVel="0" HiVel="127" RRGroup="1"
          FileName="/Users/rick/Downloads/mod/PuddinChord/PuddinChord-C2-15-11FC.aif"
          Duplicate="0" LoopEnabled="1" LoopStart="226364" LoopEnd="332861"
          SampleEnd="455296" SampleRate="44100.0" MonolithOffset="3645440"
          MonolithLength="458752"/>
  <sample Root="60" LoKey="60" HiKey="60" LoVel="0" HiVel="127" RRGroup="1"
          FileName="/Users/rick/Downloads/mod/PuddinChord/PuddinChord-C3-15-6EXP.aif"
          Duplicate="0" LoopEnabled="1" LoopStart="180914" LoopEnd="257711"
          SampleEnd="454656" SampleRate="44100.0" MonolithOffset="4104192"
          MonolithLength="454656"/>
  <sample Root="72" LoKey="72" HiKey="127" LoVel="0" HiVel="127" RRGroup="1"
          FileName="/Users/rick/Downloads/mod/PuddinChord/PuddinChord-C4-15-UZPS.aif"
          Duplicate="0" LoopEnabled="1" LoopStart="285598" LoopEnd="324148"
          SampleEnd="454016" SampleRate="44100.0" MonolithOffset="4558848"
          MonolithLength="454656"/>
  <sample Root="51" LoKey="51" HiKey="51" LoVel="0" HiVel="127" RRGroup="1"
          FileName="/Users/rick/Downloads/mod/PuddinChord/PuddinChord-D#2-15-JI2Q.aif"
          Duplicate="0" LoopEnabled="1" LoopStart="245007" LoopEnd="334551"
          SampleEnd="453984" SampleRate="44100.0" MonolithOffset="5013504"
          MonolithLength="454656"/>
  <sample Root="63" LoKey="63" HiKey="63" LoVel="0" HiVel="127" RRGroup="1"
          FileName="/Users/rick/Downloads/mod/PuddinChord/PuddinChord-D#3-15-RN0V.aif"
          Duplicate="0" LoopEnabled="1" LoopStart="199496" LoopEnd="353354"
          SampleEnd="454304" SampleRate="44100.0" MonolithOffset="5468160"
          MonolithLength="454656"/>
  <sample Root="50" LoKey="50" HiKey="50" LoVel="0" HiVel="127" RRGroup="1"
          FileName="/Users/rick/Downloads/mod/PuddinChord/PuddinChord-D2-15-8A8E.aif"
          Duplicate="0" LoopEnabled="1" LoopStart="250689" LoopEnd="345558"
          SampleEnd="454240" SampleRate="44100.0" MonolithOffset="5922816"
          MonolithLength="454656"/>
  <sample Root="62" LoKey="62" HiKey="62" LoVel="0" HiVel="127" RRGroup="1"
          FileName="/Users/rick/Downloads/mod/PuddinChord/PuddinChord-D3-15-9B8U.aif"
          Duplicate="0" LoopEnabled="1" LoopStart="214434" LoopEnd="347719"
          SampleEnd="455392" SampleRate="44100.0" MonolithOffset="6377472"
          MonolithLength="458752"/>
  <sample Root="52" LoKey="52" HiKey="52" LoVel="0" HiVel="127" RRGroup="1"
          FileName="/Users/rick/Downloads/mod/PuddinChord/PuddinChord-E2-15-73KB.aif"
          Duplicate="0" LoopEnabled="1" LoopStart="223728" LoopEnd="271607"
          SampleEnd="454496" SampleRate="44100.0" MonolithOffset="6836224"
          MonolithLength="454656"/>
  <sample Root="64" LoKey="64" HiKey="64" LoVel="0" HiVel="127" RRGroup="1"
          FileName="/Users/rick/Downloads/mod/PuddinChord/PuddinChord-E3-15-7ZLO.aif"
          Duplicate="0" LoopEnabled="1" LoopStart="175824" LoopEnd="348781"
          SampleEnd="459680" SampleRate="44100.0" MonolithOffset="7290880"
          MonolithLength="462848"/>
  <sample Root="54" LoKey="54" HiKey="54" LoVel="0" HiVel="127" RRGroup="1"
          FileName="/Users/rick/Downloads/mod/PuddinChord/PuddinChord-F#2-15-6KIW.aif"
          Duplicate="0" LoopEnabled="1" LoopStart="186964" LoopEnd="284643"
          SampleEnd="455456" SampleRate="44100.0" MonolithOffset="7753728"
          MonolithLength="458752"/>
  <sample Root="66" LoKey="66" HiKey="66" LoVel="0" HiVel="127" RRGroup="1"
          FileName="/Users/rick/Downloads/mod/PuddinChord/PuddinChord-F#3-15-E3B8.aif"
          Duplicate="0" LoopEnabled="1" LoopStart="236552" LoopEnd="290501"
          SampleEnd="453728" SampleRate="44100.0" MonolithOffset="8212480"
          MonolithLength="454656"/>
  <sample Root="53" LoKey="53" HiKey="53" LoVel="0" HiVel="127" RRGroup="1"
          FileName="/Users/rick/Downloads/mod/PuddinChord/PuddinChord-F2-15-FPIS.aif"
          Duplicate="0" LoopEnabled="1" LoopStart="208445" LoopEnd="266757"
          SampleEnd="453408" SampleRate="44100.0" MonolithOffset="8667136"
          MonolithLength="454656"/>
  <sample Root="65" LoKey="65" HiKey="65" LoVel="0" HiVel="127" RRGroup="1"
          FileName="/Users/rick/Downloads/mod/PuddinChord/PuddinChord-F3-15-NI4K.aif"
          Duplicate="0" LoopEnabled="1" LoopStart="178835" LoopEnd="312963"
          SampleEnd="453472" SampleRate="44100.0" MonolithOffset="9121792"
          MonolithLength="454656"/>
  <sample Root="56" LoKey="56" HiKey="56" LoVel="0" HiVel="127" RRGroup="1"
          FileName="/Users/rick/Downloads/mod/PuddinChord/PuddinChord-G#2-15-2FCZ.aif"
          Duplicate="0" LoopEnabled="1" LoopStart="218596" LoopEnd="256577"
          SampleEnd="454848" SampleRate="44100.0" MonolithOffset="9576448"
          MonolithLength="458752"/>
  <sample Root="68" LoKey="68" HiKey="68" LoVel="0" HiVel="127" RRGroup="1"
          FileName="/Users/rick/Downloads/mod/PuddinChord/PuddinChord-G#3-15-PFW1.aif"
          Duplicate="0" LoopEnabled="1" LoopStart="276263" LoopEnd="362415"
          SampleEnd="453120" SampleRate="44100.0" MonolithOffset="10035200"
          MonolithLength="454656"/>
  <sample Root="55" LoKey="55" HiKey="55" LoVel="0" HiVel="127" RRGroup="1"
          FileName="/Users/rick/Downloads/mod/PuddinChord/PuddinChord-G2-15-ENFC.aif"
          Duplicate="0" LoopEnabled="1" LoopStart="249644" LoopEnd="334652"
          SampleEnd="455168" SampleRate="44100.0" MonolithOffset="10489856"
          MonolithLength="458752"/>
  <sample Root="67" LoKey="67" HiKey="67" LoVel="0" HiVel="127" RRGroup="1"
          FileName="/Users/rick/Downloads/mod/PuddinChord/PuddinChord-G3-15-M64J.aif"
          Duplicate="0" LoopEnabled="1" LoopStart="278628" LoopEnd="355296"
          SampleEnd="454208" SampleRate="44100.0" MonolithOffset="10948608"
          MonolithLength="454656"/>
</samplemap>
